instant_distance-0.3.6.dist-info/METADATA
instant_distance-0.3.6.dist-info/WHEEL
instant_distance/__init__.py
instant_distance/instant_distance.cpython-311-darwin.so
instant_distance-0.3.6.dist-info/RECORD
