Metadata-Version: 2.1
Name: instant-distance
Version: 0.3.6
Summary: Fast minimal implementation of HNSW maps for approximate nearest neighbors searches
Home-Page: https://github.com/InstantDomain/instant-distance
License: MIT OR Apache-2.0
Project-URL: Source Code, https://github.com/InstantDomain/instant-distance
